awin_py/__init__.py
awin_py/advertiser_api/__init__.py
awin_py/advertiser_api/client.py
awin_py/advertiser_api/errors.py
awin_py/advertiser_api/models.py
awin_py-0.0.3.dist-info/METADATA
awin_py-0.0.3.dist-info/WHEEL
awin_py-0.0.3.dist-info/RECORD
