Metadata-Version: 2.3
Name: awin-py
Version: 0.0.3
Summary: A wrapper around the AWIN API.
Project-URL: Homepage, https://github.com/FriedrichtenHagen/awin-py
Project-URL: Issues, https://github.com/FriedrichtenHagen/awin-py/issues
Author-email: Friedrich ten Hagen <author@example.com>
Classifier: License :: OSI Approved :: MIT License
Classifier: Operating System :: OS Independent
Classifier: Programming Language :: Python :: 3
Requires-Python: >=3.8
Requires-Dist: requests>=2.31.0
